slide_patches/__init__.py
slide_patches/patches.py
slide_patches-0.0.1.dist-info/METADATA
slide_patches-0.0.1.dist-info/WHEEL
slide_patches-0.0.1.dist-info/licenses/LICENSE
slide_patches-0.0.1.dist-info/RECORD
